<?xml version="1.0" encoding="UTF-8"?>

<ImplementationGuide xmlns="http://hl7.org/fhir">
  <id value="hl7.fhir.us.pacio-splasch"/>
  <text>
    <status value="extensions"/><div xmlns="http://www.w3.org/1999/xhtml"><h2>PACIOReAssessmentTimepoints</h2><p>The official URL for this implementation guide is: </p><pre>http://hl7.org/fhir/us/pacio-splasch/ImplementationGuide/hl7.fhir.us.pacio-splasch</pre><div><p>PACIO Speech Language Swallowing Cognitive Communication and Hearing (SPLASCH) Implementation Guide</p>
</div></div>
  </text>
  <url value="http://hl7.org/fhir/us/pacio-splasch/ImplementationGuide/hl7.fhir.us.pacio-splasch"/>
  <version value="0.1.0"/>
  <name value="PACIOReAssessmentTimepoints"/>
  <title value="PACIO Speech Language Swallowing Cognitive Communication and Hearing (SPLASCH) Implementation Guide"/>
  <status value="draft"/>
  <date value="2022-03-24T23:37:25-04:00"/>
  <publisher value="HL7 Patient Care Working Group"/>
  <contact>
    <name value="HL7 Patient Care Working Group"/>
    <telecom>
      <system value="url"/>
      <value value="http://www.hl7.org/Special/committees/patientcare"/>
    </telecom>
    <telecom>
      <system value="email"/>
      <value value="patients@lists.HL7.org"/>
    </telecom>
  </contact>
  <contact>
    <name value="PACIO project"/>
    <telecom>
      <system value="url"/>
      <value value="http://www.hl7.org/Special/committees/patientcare"/>
    </telecom>
    <telecom>
      <system value="email"/>
      <value value="info@pacioproject.org"/>
    </telecom>
  </contact>
  <description value="PACIO Speech Language Swallowing Cognitive Communication and Hearing (SPLASCH) Implementation Guide"/>
  <jurisdiction>
    <coding>
      <system value="urn:iso:std:iso:3166"/>
      <code value="US"/>
    </coding>
  </jurisdiction>
  <packageId value="hl7.fhir.us.pacio-splasch"/>
  <license value="CC0-1.0"/>
  <fhirVersion value="4.0.1"/>
  <dependsOn id="hl7_fhir_us_core">
    <uri value="http://hl7.org/fhir/us/core/ImplementationGuide/hl7.fhir.us.core"/>
    <packageId value="hl7.fhir.us.core"/>
    <version value="4.0.0"/>
  </dependsOn>
  <definition>
    <extension url="http://hl7.org/fhir/tools/StructureDefinition/ig-parameter">
      <extension url="code">
        <valueString value="copyrightyear"/>
      </extension>
      <extension url="value">
        <valueString value="2021+"/>
      </extension>
    </extension>
    <extension url="http://hl7.org/fhir/tools/StructureDefinition/ig-parameter">
      <extension url="code">
        <valueString value="releaselabel"/>
      </extension>
      <extension url="value">
        <valueString value="ci-build"/>
      </extension>
    </extension>
    <extension url="http://hl7.org/fhir/tools/StructureDefinition/ig-parameter">
      <extension url="code">
        <valueString value="path-expansion-params"/>
      </extension>
      <extension url="value">
        <valueString value="../../input/_resources/terminology-settings.json"/>
      </extension>
    </extension>
    <extension url="http://hl7.org/fhir/tools/StructureDefinition/ig-parameter">
      <extension url="code">
        <valueString value="show-inherited-invariants"/>
      </extension>
      <extension url="value">
        <valueString value="false"/>
      </extension>
    </extension>
    <extension url="http://hl7.org/fhir/tools/StructureDefinition/ig-parameter">
      <extension url="code">
        <valueString value="apply-jurisdiction"/>
      </extension>
      <extension url="value">
        <valueString value="true"/>
      </extension>
    </extension>
    <extension url="http://hl7.org/fhir/tools/StructureDefinition/ig-parameter">
      <extension url="code">
        <valueString value="apply-publisher"/>
      </extension>
      <extension url="value">
        <valueString value="true"/>
      </extension>
    </extension>
    <extension url="http://hl7.org/fhir/tools/StructureDefinition/ig-parameter">
      <extension url="code">
        <valueString value="path-history"/>
      </extension>
      <extension url="value">
        <valueString value="http://hl7.org/fhir/us/pacio-splasch/history.html"/>
      </extension>
    </extension>
    <extension url="http://hl7.org/fhir/tools/StructureDefinition/ig-parameter">
      <extension url="code">
        <valueString value="autoload-resources"/>
      </extension>
      <extension url="value">
        <valueString value="true"/>
      </extension>
    </extension>
    <extension url="http://hl7.org/fhir/tools/StructureDefinition/ig-parameter">
      <extension url="code">
        <valueString value="path-liquid"/>
      </extension>
      <extension url="value">
        <valueString value="template/liquid"/>
      </extension>
    </extension>
    <extension url="http://hl7.org/fhir/tools/StructureDefinition/ig-parameter">
      <extension url="code">
        <valueString value="path-liquid"/>
      </extension>
      <extension url="value">
        <valueString value="input/liquid"/>
      </extension>
    </extension>
    <extension url="http://hl7.org/fhir/tools/StructureDefinition/ig-parameter">
      <extension url="code">
        <valueString value="path-qa"/>
      </extension>
      <extension url="value">
        <valueString value="temp/qa"/>
      </extension>
    </extension>
    <extension url="http://hl7.org/fhir/tools/StructureDefinition/ig-parameter">
      <extension url="code">
        <valueString value="path-temp"/>
      </extension>
      <extension url="value">
        <valueString value="temp/pages"/>
      </extension>
    </extension>
    <extension url="http://hl7.org/fhir/tools/StructureDefinition/ig-parameter">
      <extension url="code">
        <valueString value="path-output"/>
      </extension>
      <extension url="value">
        <valueString value="output"/>
      </extension>
    </extension>
    <extension url="http://hl7.org/fhir/tools/StructureDefinition/ig-parameter">
      <extension url="code">
        <valueString value="path-suppressed-warnings"/>
      </extension>
      <extension url="value">
        <valueString value="input/ignoreWarnings.txt"/>
      </extension>
    </extension>
    <extension url="http://hl7.org/fhir/tools/StructureDefinition/ig-parameter">
      <extension url="code">
        <valueString value="template-html"/>
      </extension>
      <extension url="value">
        <valueString value="template-page.html"/>
      </extension>
    </extension>
    <extension url="http://hl7.org/fhir/tools/StructureDefinition/ig-parameter">
      <extension url="code">
        <valueString value="template-md"/>
      </extension>
      <extension url="value">
        <valueString value="template-page-md.html"/>
      </extension>
    </extension>
    <extension url="http://hl7.org/fhir/tools/StructureDefinition/ig-parameter">
      <extension url="code">
        <valueString value="apply-contact"/>
      </extension>
      <extension url="value">
        <valueString value="true"/>
      </extension>
    </extension>
    <extension url="http://hl7.org/fhir/tools/StructureDefinition/ig-parameter">
      <extension url="code">
        <valueString value="apply-context"/>
      </extension>
      <extension url="value">
        <valueString value="true"/>
      </extension>
    </extension>
    <extension url="http://hl7.org/fhir/tools/StructureDefinition/ig-parameter">
      <extension url="code">
        <valueString value="apply-copyright"/>
      </extension>
      <extension url="value">
        <valueString value="true"/>
      </extension>
    </extension>
    <extension url="http://hl7.org/fhir/tools/StructureDefinition/ig-parameter">
      <extension url="code">
        <valueString value="apply-license"/>
      </extension>
      <extension url="value">
        <valueString value="true"/>
      </extension>
    </extension>
    <extension url="http://hl7.org/fhir/tools/StructureDefinition/ig-parameter">
      <extension url="code">
        <valueString value="apply-version"/>
      </extension>
      <extension url="value">
        <valueString value="true"/>
      </extension>
    </extension>
    <extension url="http://hl7.org/fhir/tools/StructureDefinition/ig-parameter">
      <extension url="code">
        <valueString value="active-tables"/>
      </extension>
      <extension url="value">
        <valueString value="true"/>
      </extension>
    </extension>
    <extension url="http://hl7.org/fhir/tools/StructureDefinition/ig-parameter">
      <extension url="code">
        <valueString value="fmm-definition"/>
      </extension>
      <extension url="value">
        <valueString value="http://hl7.org/fhir/versions.html#maturity"/>
      </extension>
    </extension>
    <extension url="http://hl7.org/fhir/tools/StructureDefinition/ig-parameter">
      <extension url="code">
        <valueString value="propagate-status"/>
      </extension>
      <extension url="value">
        <valueString value="true"/>
      </extension>
    </extension>
    <resource>
      <extension url="http://hl7.org/fhir/tools/StructureDefinition/resource-information">
        <valueString value="StructureDefinition:resource"/>
      </extension>
      <reference>
        <reference value="StructureDefinition/splasch-HearingObservation"/>
      </reference>
      <name value="Hearing Observation"/>
      <description value="An exchange of hearing data for a patient."/>
      <exampleBoolean value="false"/>
    </resource>
    <resource>
      <extension url="http://hl7.org/fhir/tools/StructureDefinition/resource-information">
        <valueString value="StructureDefinition:resource"/>
      </extension>
      <reference>
        <reference value="StructureDefinition/splasch-MultiModalCommunicationObservation"/>
      </reference>
      <name value="Multi-Modal Communication Observation"/>
      <description value="An exchange of multi-modal communication data for a patient."/>
      <exampleBoolean value="false"/>
    </resource>
    <resource>
      <extension url="http://hl7.org/fhir/tools/StructureDefinition/resource-information">
        <valueString value="StructureDefinition:resource"/>
      </extension>
      <reference>
        <reference value="StructureDefinition/splasch-SpokenLanguageComprehensionObservation"/>
      </reference>
      <name value="Spoken Language Comprehension Observation"/>
      <description value="An exchange of spoken language comprehension data for a patient."/>
      <exampleBoolean value="false"/>
    </resource>
    <resource>
      <extension url="http://hl7.org/fhir/tools/StructureDefinition/resource-information">
        <valueString value="StructureDefinition:resource"/>
      </extension>
      <reference>
        <reference value="StructureDefinition/splasch-SpokenLanguageExpressionObservation"/>
      </reference>
      <name value="Spoken Language Expression Observation"/>
      <description value="An exchange of spoken language expression data for a patient."/>
      <exampleBoolean value="false"/>
    </resource>
    <resource>
      <extension url="http://hl7.org/fhir/tools/StructureDefinition/resource-information">
        <valueString value="StructureDefinition:resource"/>
      </extension>
      <reference>
        <reference value="StructureDefinition/splasch-SwallowingObservation"/>
      </reference>
      <name value="Swallowing Observation"/>
      <description value="An exchange of swallowing data for a patient."/>
      <exampleBoolean value="false"/>
    </resource>
    <resource>
      <extension url="http://hl7.org/fhir/tools/StructureDefinition/resource-information">
        <valueString value="ValueSet"/>
      </extension>
      <reference>
        <reference value="ValueSet/CmsFasiAssistiveDevicesVS"/>
      </reference>
      <name value="CMS FASI Assistive Devices"/>
      <description value="SPLASCH hearing observation codes representing answers to need for and availability of a hearing aid"/>
      <exampleBoolean value="false"/>
    </resource>
    <resource>
      <extension url="http://hl7.org/fhir/tools/StructureDefinition/resource-information">
        <valueString value="ValueSet"/>
      </extension>
      <reference>
        <reference value="ValueSet/HearingAbilityToHearDuringAssessmentPeriodVS"/>
      </reference>
      <name value="Hearing Ability to Hear During Assessment Period"/>
      <description value="SPLASCH hearing observation codes representing answers to ability to hear during assessment period"/>
      <exampleBoolean value="false"/>
    </resource>
    <resource>
      <extension url="http://hl7.org/fhir/tools/StructureDefinition/resource-information">
        <valueString value="ValueSet"/>
      </extension>
      <reference>
        <reference value="ValueSet/SPLASCHCaloriePercentageTypeObservationVS"/>
      </reference>
      <name value="Calorie Percentage Type Observation"/>
      <description value="ValueSet identifying observation codes that have a calorie percentage value. This ValueSet can be used for creating a pick-list or value validation appropriate for a particular observation."/>
      <exampleBoolean value="false"/>
    </resource>
    <resource>
      <extension url="http://hl7.org/fhir/tools/StructureDefinition/resource-information">
        <valueString value="ValueSet"/>
      </extension>
      <reference>
        <reference value="ValueSet/SPLASCHFrequencyObservationVS"/>
      </reference>
      <name value="SPLASCH Frequency Observation Values"/>
      <description value="Frequency values for SPLASCH observations"/>
      <exampleBoolean value="false"/>
    </resource>
    <resource>
      <extension url="http://hl7.org/fhir/tools/StructureDefinition/resource-information">
        <valueString value="ValueSet"/>
      </extension>
      <reference>
        <reference value="ValueSet/SPLASCHFrequencyTypeObservationVS"/>
      </reference>
      <name value="Frequency Type Observation"/>
      <description value="ValueSet identifying observation codes that have a frequency value. This ValueSet can be used for creating a pick-list or value validation appropriate for a particular observation."/>
      <exampleBoolean value="false"/>
    </resource>
    <resource>
      <extension url="http://hl7.org/fhir/tools/StructureDefinition/resource-information">
        <valueString value="ValueSet"/>
      </extension>
      <reference>
        <reference value="ValueSet/SPLASCHHearingObservationVS"/>
      </reference>
      <name value="Hearing Observation"/>
      <description value="SPLASCH hearing observation profile: codes representing hearing questions that are answered by the ValueSet SPLASCHHearingObservationValueCodeableConceptVS"/>
      <exampleBoolean value="false"/>
    </resource>
    <resource>
      <extension url="http://hl7.org/fhir/tools/StructureDefinition/resource-information">
        <valueString value="ValueSet"/>
      </extension>
      <reference>
        <reference value="ValueSet/SPLASCHHearingObservationValueVS"/>
      </reference>
      <name value="Hearing Observation Value"/>
      <description value="SPLASCH hearing observation values: codes representing answers to the hearing questions asked by the ValueSet SPLASCHHearingObservationCodeVS"/>
      <exampleBoolean value="false"/>
    </resource>
    <resource>
      <extension url="http://hl7.org/fhir/tools/StructureDefinition/resource-information">
        <valueString value="ValueSet"/>
      </extension>
      <reference>
        <reference value="ValueSet/SPLASCHLiquidDietModifierTypeObservationVS"/>
      </reference>
      <name value="Liquid Diet Modifier Type Observation"/>
      <description value="ValueSet identifying observation codes that have a liquid diet modifier value. This ValueSet can be used for creating a pick-list or value validation appropriate for a particular observation."/>
      <exampleBoolean value="false"/>
    </resource>
    <resource>
      <extension url="http://hl7.org/fhir/tools/StructureDefinition/resource-information">
        <valueString value="ValueSet"/>
      </extension>
      <reference>
        <reference value="ValueSet/SPLASCHMultiModalCommunicationObservationVS"/>
      </reference>
      <name value="Multi-Modal Communication Observation"/>
      <description value="SPLASCH multi-modal communication observation profile"/>
      <exampleBoolean value="false"/>
    </resource>
    <resource>
      <extension url="http://hl7.org/fhir/tools/StructureDefinition/resource-information">
        <valueString value="ValueSet"/>
      </extension>
      <reference>
        <reference value="ValueSet/SPLASCHObservationCategoryVS"/>
      </reference>
      <name value="SPLASCH Observation Category"/>
      <description value="Categories for SPLASCH observation profiles"/>
      <exampleBoolean value="false"/>
    </resource>
    <resource>
      <extension url="http://hl7.org/fhir/tools/StructureDefinition/resource-information">
        <valueString value="ValueSet"/>
      </extension>
      <reference>
        <reference value="ValueSet/SPLASCHSolidDietModifierTypeObservationVS"/>
      </reference>
      <name value="Solid Diet Modifier Type Observation"/>
      <description value="ValueSet identifying observation codes that have a solid diet modifier value. This ValueSet can be used for creating a pick-list or value validation appropriate for a particular observation."/>
      <exampleBoolean value="false"/>
    </resource>
    <resource>
      <extension url="http://hl7.org/fhir/tools/StructureDefinition/resource-information">
        <valueString value="ValueSet"/>
      </extension>
      <reference>
        <reference value="ValueSet/SPLASCHSpeechComprehensionObservationVS"/>
      </reference>
      <name value="Speech Comprehension Observation"/>
      <description value="SPLASCH spoken language comprehension observation profile"/>
      <exampleBoolean value="false"/>
    </resource>
    <resource>
      <extension url="http://hl7.org/fhir/tools/StructureDefinition/resource-information">
        <valueString value="ValueSet"/>
      </extension>
      <reference>
        <reference value="ValueSet/SPLASCHSpeechExpressionObservationVS"/>
      </reference>
      <name value="Speech Expression Observation"/>
      <description value="SPLASCH spoken language expression observation profile"/>
      <exampleBoolean value="false"/>
    </resource>
    <resource>
      <extension url="http://hl7.org/fhir/tools/StructureDefinition/resource-information">
        <valueString value="ValueSet"/>
      </extension>
      <reference>
        <reference value="ValueSet/SPLASCHSwallowingObservationVS"/>
      </reference>
      <name value="Swallowing Observation"/>
      <description value="SPLASCH swallowing observation profile"/>
      <exampleBoolean value="false"/>
    </resource>
    <resource>
      <extension url="http://hl7.org/fhir/tools/StructureDefinition/resource-information">
        <valueString value="ValueSet"/>
      </extension>
      <reference>
        <reference value="ValueSet/SPLASCHSwallowingObservationValueVS"/>
      </reference>
      <name value="Swallowing Observation Value"/>
      <description value="Values for swallowing observations"/>
      <exampleBoolean value="false"/>
    </resource>
    <resource>
      <extension url="http://hl7.org/fhir/tools/StructureDefinition/resource-information">
        <valueString value="ValueSet"/>
      </extension>
      <reference>
        <reference value="ValueSet/YesOrNoVS"/>
      </reference>
      <name value="Y/N"/>
      <description value="Yes or No"/>
      <exampleBoolean value="false"/>
    </resource>
    <resource>
      <extension url="http://hl7.org/fhir/tools/StructureDefinition/resource-information">
        <valueString value="CodeSystem"/>
      </extension>
      <reference>
        <reference value="CodeSystem/SPLASCHCaloriePercentageCategoryCS"/>
      </reference>
      <name value="Observation Value Calorie Percentage Category Codes"/>
      <description value="Category codes for calorie percentage observations"/>
      <exampleBoolean value="false"/>
    </resource>
    <resource>
      <extension url="http://hl7.org/fhir/tools/StructureDefinition/resource-information">
        <valueString value="CodeSystem"/>
      </extension>
      <reference>
        <reference value="CodeSystem/SPLASCHLiquidDietCS"/>
      </reference>
      <name value="Observation Value Liquid Diet Codes"/>
      <description value="Category codes for liquid diet observations"/>
      <exampleBoolean value="false"/>
    </resource>
    <resource>
      <extension url="http://hl7.org/fhir/tools/StructureDefinition/resource-information">
        <valueString value="CodeSystem"/>
      </extension>
      <reference>
        <reference value="CodeSystem/SPLASCHMultiModalCommunicationObservationCS"/>
      </reference>
      <name value="Multi-Modal Communication Observation Codes"/>
      <description value="Observation codes for multi-modal communication"/>
      <exampleBoolean value="false"/>
    </resource>
    <resource>
      <extension url="http://hl7.org/fhir/tools/StructureDefinition/resource-information">
        <valueString value="CodeSystem"/>
      </extension>
      <reference>
        <reference value="CodeSystem/SPLASCHObservationCategoryCS"/>
      </reference>
      <name value="SPLASCH Observation Category Codes"/>
      <description value="Categories for SPLASCH observations"/>
      <exampleBoolean value="false"/>
    </resource>
    <resource>
      <extension url="http://hl7.org/fhir/tools/StructureDefinition/resource-information">
        <valueString value="CodeSystem"/>
      </extension>
      <reference>
        <reference value="CodeSystem/SPLASCHSolidDietCS"/>
      </reference>
      <name value="Observation Value Solid Diet Codes"/>
      <description value="Category codes for solid diet observations"/>
      <exampleBoolean value="false"/>
    </resource>
    <resource>
      <extension url="http://hl7.org/fhir/tools/StructureDefinition/resource-information">
        <valueString value="CodeSystem"/>
      </extension>
      <reference>
        <reference value="CodeSystem/SPLASCHSpeechComprehensionObservationCS"/>
      </reference>
      <name value="Speech Comprehension Observation Codes"/>
      <description value="Observation codes for spoken language comprehension"/>
      <exampleBoolean value="false"/>
    </resource>
    <resource>
      <extension url="http://hl7.org/fhir/tools/StructureDefinition/resource-information">
        <valueString value="CodeSystem"/>
      </extension>
      <reference>
        <reference value="CodeSystem/SPLASCHSpeechExpressionObservationCS"/>
      </reference>
      <name value="Speech Expression Observation Codes"/>
      <description value="Observation codes for spoken language expression"/>
      <exampleBoolean value="false"/>
    </resource>
    <resource>
      <extension url="http://hl7.org/fhir/tools/StructureDefinition/resource-information">
        <valueString value="CodeSystem"/>
      </extension>
      <reference>
        <reference value="CodeSystem/SPLASCHSwallowingObservationCS"/>
      </reference>
      <name value="Swallowing Observation Codes"/>
      <description value="Observation codes for swallowing"/>
      <exampleBoolean value="false"/>
    </resource>
    <resource>
      <extension url="http://hl7.org/fhir/tools/StructureDefinition/resource-information">
        <valueString value="CodeSystem"/>
      </extension>
      <reference>
        <reference value="CodeSystem/SPLASCHTimePercentageCategoryCS"/>
      </reference>
      <name value="Observation Value Time Percentage Category Codes"/>
      <description value="Catgegory codes for time percentage observations"/>
      <exampleBoolean value="false"/>
    </resource>
    <resource>
      <extension url="http://hl7.org/fhir/tools/StructureDefinition/resource-information">
        <valueString value="Observation"/>
      </extension>
      <reference>
        <reference value="Observation/BSJ-ObservationSPLASCH-001"/>
      </reference>
      <name value="BSJ-ObservationSPLASCH-001"/>
      <description value="An instance of SPLASCH Observation ObservationSPLASCH-001"/>
      <exampleBoolean value="true"/>
    </resource>
    <resource>
      <extension url="http://hl7.org/fhir/tools/StructureDefinition/resource-information">
        <valueString value="Observation"/>
      </extension>
      <reference>
        <reference value="Observation/BSJ-ObservationSPLASCH-002"/>
      </reference>
      <name value="BSJ-ObservationSPLASCH-002"/>
      <description value="An instance of SPLASCH Observation ObservationSPLASCH-002"/>
      <exampleBoolean value="true"/>
    </resource>
    <resource>
      <extension url="http://hl7.org/fhir/tools/StructureDefinition/resource-information">
        <valueString value="Observation"/>
      </extension>
      <reference>
        <reference value="Observation/BSJ-ObservationSPLASCH-003"/>
      </reference>
      <name value="BSJ-ObservationSPLASCH-003"/>
      <description value="An instance of SPLASCH Observation ObservationSPLASCH-003"/>
      <exampleBoolean value="true"/>
    </resource>
    <resource>
      <extension url="http://hl7.org/fhir/tools/StructureDefinition/resource-information">
        <valueString value="Observation"/>
      </extension>
      <reference>
        <reference value="Observation/BSJ-ObservationSPLASCH-004"/>
      </reference>
      <name value="BSJ-ObservationSPLASCH-004"/>
      <description value="An instance of SPLASCH Observation ObservationSPLASCH-004"/>
      <exampleBoolean value="true"/>
    </resource>
    <resource>
      <extension url="http://hl7.org/fhir/tools/StructureDefinition/resource-information">
        <valueString value="Observation"/>
      </extension>
      <reference>
        <reference value="Observation/BSJ-ObservationSPLASCH-005"/>
      </reference>
      <name value="BSJ-ObservationSPLASCH-005"/>
      <description value="An instance of SPLASCH Observation ObservationSPLASCH-005"/>
      <exampleBoolean value="true"/>
    </resource>
    <resource>
      <extension url="http://hl7.org/fhir/tools/StructureDefinition/resource-information">
        <valueString value="Observation"/>
      </extension>
      <reference>
        <reference value="Observation/BSJ-ObservationSPLASCH-006"/>
      </reference>
      <name value="BSJ-ObservationSPLASCH-006"/>
      <description value="An instance of SPLASCH Observation ObservationSPLASCH-006"/>
      <exampleBoolean value="true"/>
    </resource>
    <resource>
      <extension url="http://hl7.org/fhir/tools/StructureDefinition/resource-information">
        <valueString value="Observation"/>
      </extension>
      <reference>
        <reference value="Observation/BSJ-ObservationSPLASCH-007"/>
      </reference>
      <name value="BSJ-ObservationSPLASCH-007"/>
      <description value="An instance of SPLASCH Observation ObservationSPLASCH-007"/>
      <exampleBoolean value="true"/>
    </resource>
    <resource>
      <extension url="http://hl7.org/fhir/tools/StructureDefinition/resource-information">
        <valueString value="Observation"/>
      </extension>
      <reference>
        <reference value="Observation/BSJ-ObservationSPLASCH-008"/>
      </reference>
      <name value="BSJ-ObservationSPLASCH-008"/>
      <description value="An instance of SPLASCH Observation ObservationSPLASCH-008"/>
      <exampleBoolean value="true"/>
    </resource>
    <resource>
      <extension url="http://hl7.org/fhir/tools/StructureDefinition/resource-information">
        <valueString value="Observation"/>
      </extension>
      <reference>
        <reference value="Observation/BSJ-ObservationSPLASCH-009"/>
      </reference>
      <name value="BSJ-ObservationSPLASCH-009"/>
      <description value="An instance of SPLASCH Observation ObservationSPLASCH-009"/>
      <exampleBoolean value="true"/>
    </resource>
    <resource>
      <extension url="http://hl7.org/fhir/tools/StructureDefinition/resource-information">
        <valueString value="Observation"/>
      </extension>
      <reference>
        <reference value="Observation/BSJ-ObservationSPLASCH-010"/>
      </reference>
      <name value="BSJ-ObservationSPLASCH-010"/>
      <description value="An instance of SPLASCH Observation ObservationSPLASCH-010"/>
      <exampleBoolean value="true"/>
    </resource>
    <resource>
      <extension url="http://hl7.org/fhir/tools/StructureDefinition/resource-information">
        <valueString value="Observation"/>
      </extension>
      <reference>
        <reference value="Observation/BSJ-ObservationSPLASCH-011"/>
      </reference>
      <name value="BSJ-ObservationSPLASCH-011"/>
      <description value="An instance of SPLASCH Observation ObservationSPLASCH-011"/>
      <exampleBoolean value="true"/>
    </resource>
    <resource>
      <extension url="http://hl7.org/fhir/tools/StructureDefinition/resource-information">
        <valueString value="Observation"/>
      </extension>
      <reference>
        <reference value="Observation/BSJ-ObservationSPLASCH-012"/>
      </reference>
      <name value="BSJ-ObservationSPLASCH-012"/>
      <description value="An instance of SPLASCH Observation ObservationSPLASCH-012"/>
      <exampleBoolean value="true"/>
    </resource>
    <resource>
      <extension url="http://hl7.org/fhir/tools/StructureDefinition/resource-information">
        <valueString value="Observation"/>
      </extension>
      <reference>
        <reference value="Observation/BSJ-ObservationSPLASCH-013"/>
      </reference>
      <name value="BSJ-ObservationSPLASCH-013"/>
      <description value="An instance of SPLASCH Observation ObservationSPLASCH-013"/>
      <exampleBoolean value="true"/>
    </resource>
    <resource>
      <extension url="http://hl7.org/fhir/tools/StructureDefinition/resource-information">
        <valueString value="Observation"/>
      </extension>
      <reference>
        <reference value="Observation/BSJ-ObservationSPLASCH-014"/>
      </reference>
      <name value="BSJ-ObservationSPLASCH-014"/>
      <description value="An instance of SPLASCH Observation ObservationSPLASCH-014"/>
      <exampleBoolean value="true"/>
    </resource>
    <resource>
      <extension url="http://hl7.org/fhir/tools/StructureDefinition/resource-information">
        <valueString value="Observation"/>
      </extension>
      <reference>
        <reference value="Observation/BSJ-ObservationSPLASCH-015"/>
      </reference>
      <name value="BSJ-ObservationSPLASCH-015"/>
      <description value="An instance of SPLASCH Observation ObservationSPLASCH-015"/>
      <exampleBoolean value="true"/>
    </resource>
    <resource>
      <extension url="http://hl7.org/fhir/tools/StructureDefinition/resource-information">
        <valueString value="Observation"/>
      </extension>
      <reference>
        <reference value="Observation/BSJ-ObservationSPLASCH-016"/>
      </reference>
      <name value="BSJ-ObservationSPLASCH-016"/>
      <description value="An instance of SPLASCH Observation ObservationSPLASCH-016"/>
      <exampleBoolean value="true"/>
    </resource>
    <resource>
      <extension url="http://hl7.org/fhir/tools/StructureDefinition/resource-information">
        <valueString value="Observation"/>
      </extension>
      <reference>
        <reference value="Observation/BSJ-ObservationSPLASCH-017"/>
      </reference>
      <name value="BSJ-ObservationSPLASCH-017"/>
      <description value="An instance of SPLASCH Observation ObservationSPLASCH-017"/>
      <exampleBoolean value="true"/>
    </resource>
    <resource>
      <extension url="http://hl7.org/fhir/tools/StructureDefinition/resource-information">
        <valueString value="Observation"/>
      </extension>
      <reference>
        <reference value="Observation/BSJ-ObservationSPLASCH-018"/>
      </reference>
      <name value="BSJ-ObservationSPLASCH-018"/>
      <description value="An instance of SPLASCH Observation ObservationSPLASCH-018"/>
      <exampleBoolean value="true"/>
    </resource>
    <resource>
      <extension url="http://hl7.org/fhir/tools/StructureDefinition/resource-information">
        <valueString value="Observation"/>
      </extension>
      <reference>
        <reference value="Observation/BSJ-ObservationSPLASCH-019"/>
      </reference>
      <name value="BSJ-ObservationSPLASCH-019"/>
      <description value="An instance of SPLASCH Observation ObservationSPLASCH-019"/>
      <exampleBoolean value="true"/>
    </resource>
    <resource>
      <extension url="http://hl7.org/fhir/tools/StructureDefinition/resource-information">
        <valueString value="Observation"/>
      </extension>
      <reference>
        <reference value="Observation/BSJ-ObservationSPLASCH-020"/>
      </reference>
      <name value="BSJ-ObservationSPLASCH-020"/>
      <description value="An instance of SPLASCH Observation ObservationSPLASCH-020"/>
      <exampleBoolean value="true"/>
    </resource>
    <resource>
      <extension url="http://hl7.org/fhir/tools/StructureDefinition/resource-information">
        <valueString value="Observation"/>
      </extension>
      <reference>
        <reference value="Observation/BSJ-ObservationSPLASCH-021"/>
      </reference>
      <name value="BSJ-ObservationSPLASCH-021"/>
      <description value="An instance of SPLASCH Observation ObservationSPLASCH-021"/>
      <exampleBoolean value="true"/>
    </resource>
    <resource>
      <extension url="http://hl7.org/fhir/tools/StructureDefinition/resource-information">
        <valueString value="Observation"/>
      </extension>
      <reference>
        <reference value="Observation/BSJ-ObservationSPLASCH-022"/>
      </reference>
      <name value="BSJ-ObservationSPLASCH-022"/>
      <description value="An instance of SPLASCH Observation ObservationSPLASCH-022"/>
      <exampleBoolean value="true"/>
    </resource>
    <resource>
      <extension url="http://hl7.org/fhir/tools/StructureDefinition/resource-information">
        <valueString value="Observation"/>
      </extension>
      <reference>
        <reference value="Observation/BSJ-ObservationSPLASCH-023"/>
      </reference>
      <name value="BSJ-ObservationSPLASCH-023"/>
      <description value="An instance of SPLASCH Observation ObservationSPLASCH-023"/>
      <exampleBoolean value="true"/>
    </resource>
    <resource>
      <extension url="http://hl7.org/fhir/tools/StructureDefinition/resource-information">
        <valueString value="Observation"/>
      </extension>
      <reference>
        <reference value="Observation/BSJ-ObservationSPLASCH-024"/>
      </reference>
      <name value="BSJ-ObservationSPLASCH-024"/>
      <description value="An instance of SPLASCH Observation ObservationSPLASCH-024"/>
      <exampleBoolean value="true"/>
    </resource>
    <resource>
      <extension url="http://hl7.org/fhir/tools/StructureDefinition/resource-information">
        <valueString value="Observation"/>
      </extension>
      <reference>
        <reference value="Observation/BSJ-ObservationSPLASCH-025"/>
      </reference>
      <name value="BSJ-ObservationSPLASCH-025"/>
      <description value="An instance of SPLASCH Observation ObservationSPLASCH-025"/>
      <exampleBoolean value="true"/>
    </resource>
    <resource>
      <extension url="http://hl7.org/fhir/tools/StructureDefinition/resource-information">
        <valueString value="Observation"/>
      </extension>
      <reference>
        <reference value="Observation/BSJ-ObservationSPLASCH-026"/>
      </reference>
      <name value="BSJ-ObservationSPLASCH-026"/>
      <description value="An instance of SPLASCH Observation ObservationSPLASCH-026"/>
      <exampleBoolean value="true"/>
    </resource>
    <resource>
      <extension url="http://hl7.org/fhir/tools/StructureDefinition/resource-information">
        <valueString value="Observation"/>
      </extension>
      <reference>
        <reference value="Observation/BSJ-ObservationSPLASCH-027"/>
      </reference>
      <name value="BSJ-ObservationSPLASCH-027"/>
      <description value="An instance of SPLASCH Observation ObservationSPLASCH-027"/>
      <exampleBoolean value="true"/>
    </resource>
    <resource>
      <extension url="http://hl7.org/fhir/tools/StructureDefinition/resource-information">
        <valueString value="Observation"/>
      </extension>
      <reference>
        <reference value="Observation/BSJ-ObservationSPLASCH-028"/>
      </reference>
      <name value="BSJ-ObservationSPLASCH-028"/>
      <description value="An instance of SPLASCH Observation ObservationSPLASCH-028"/>
      <exampleBoolean value="true"/>
    </resource>
    <resource>
      <extension url="http://hl7.org/fhir/tools/StructureDefinition/resource-information">
        <valueString value="Observation"/>
      </extension>
      <reference>
        <reference value="Observation/BSJ-ObservationSPLASCH-029"/>
      </reference>
      <name value="BSJ-ObservationSPLASCH-029"/>
      <description value="An instance of SPLASCH Observation ObservationSPLASCH-029"/>
      <exampleBoolean value="true"/>
    </resource>
    <resource>
      <extension url="http://hl7.org/fhir/tools/StructureDefinition/resource-information">
        <valueString value="Observation"/>
      </extension>
      <reference>
        <reference value="Observation/BSJ-ObservationSPLASCH-030"/>
      </reference>
      <name value="BSJ-ObservationSPLASCH-030"/>
      <description value="An instance of SPLASCH Observation ObservationSPLASCH-030"/>
      <exampleBoolean value="true"/>
    </resource>
    <resource>
      <extension url="http://hl7.org/fhir/tools/StructureDefinition/resource-information">
        <valueString value="Observation"/>
      </extension>
      <reference>
        <reference value="Observation/BSJ-ObservationSPLASCH-031"/>
      </reference>
      <name value="BSJ-ObservationSPLASCH-031"/>
      <description value="An instance of SPLASCH Observation ObservationSPLASCH-031"/>
      <exampleBoolean value="true"/>
    </resource>
    <resource>
      <extension url="http://hl7.org/fhir/tools/StructureDefinition/resource-information">
        <valueString value="Observation"/>
      </extension>
      <reference>
        <reference value="Observation/BSJ-ObservationSPLASCH-032"/>
      </reference>
      <name value="BSJ-ObservationSPLASCH-032"/>
      <description value="An instance of SPLASCH Observation ObservationSPLASCH-032"/>
      <exampleBoolean value="true"/>
    </resource>
    <resource>
      <extension url="http://hl7.org/fhir/tools/StructureDefinition/resource-information">
        <valueString value="Observation"/>
      </extension>
      <reference>
        <reference value="Observation/BSJ-ObservationSPLASCH-033"/>
      </reference>
      <name value="BSJ-ObservationSPLASCH-033"/>
      <description value="An instance of SPLASCH Observation ObservationSPLASCH-033"/>
      <exampleBoolean value="true"/>
    </resource>
    <resource>
      <extension url="http://hl7.org/fhir/tools/StructureDefinition/resource-information">
        <valueString value="Observation"/>
      </extension>
      <reference>
        <reference value="Observation/BSJ-ObservationSPLASCH-034"/>
      </reference>
      <name value="BSJ-ObservationSPLASCH-034"/>
      <description value="An instance of SPLASCH Observation ObservationSPLASCH-034"/>
      <exampleBoolean value="true"/>
    </resource>
    <resource>
      <extension url="http://hl7.org/fhir/tools/StructureDefinition/resource-information">
        <valueString value="Observation"/>
      </extension>
      <reference>
        <reference value="Observation/BSJ-ObservationSPLASCH-035"/>
      </reference>
      <name value="BSJ-ObservationSPLASCH-035"/>
      <description value="An instance of SPLASCH Observation ObservationSPLASCH-035"/>
      <exampleBoolean value="true"/>
    </resource>
    <resource>
      <extension url="http://hl7.org/fhir/tools/StructureDefinition/resource-information">
        <valueString value="Observation"/>
      </extension>
      <reference>
        <reference value="Observation/BSJ-ObservationSPLASCH-036"/>
      </reference>
      <name value="BSJ-ObservationSPLASCH-036"/>
      <description value="An instance of SPLASCH Observation ObservationSPLASCH-036"/>
      <exampleBoolean value="true"/>
    </resource>
    <resource>
      <extension url="http://hl7.org/fhir/tools/StructureDefinition/resource-information">
        <valueString value="Observation"/>
      </extension>
      <reference>
        <reference value="Observation/BSJ-ObservationSPLASCH-037"/>
      </reference>
      <name value="BSJ-ObservationSPLASCH-037"/>
      <description value="An instance of SPLASCH Observation ObservationSPLASCH-037"/>
      <exampleBoolean value="true"/>
    </resource>
    <resource>
      <extension url="http://hl7.org/fhir/tools/StructureDefinition/resource-information">
        <valueString value="Observation"/>
      </extension>
      <reference>
        <reference value="Observation/BSJ-ObservationSPLASCH-038"/>
      </reference>
      <name value="BSJ-ObservationSPLASCH-038"/>
      <description value="An instance of SPLASCH Observation ObservationSPLASCH-038"/>
      <exampleBoolean value="true"/>
    </resource>
    <resource>
      <extension url="http://hl7.org/fhir/tools/StructureDefinition/resource-information">
        <valueString value="Observation"/>
      </extension>
      <reference>
        <reference value="Observation/BSJ-ObservationSPLASCH-039"/>
      </reference>
      <name value="BSJ-ObservationSPLASCH-039"/>
      <description value="An instance of SPLASCH Observation ObservationSPLASCH-039"/>
      <exampleBoolean value="true"/>
    </resource>
    <resource>
      <extension url="http://hl7.org/fhir/tools/StructureDefinition/resource-information">
        <valueString value="Observation"/>
      </extension>
      <reference>
        <reference value="Observation/BSJ-ObservationSPLASCH-040"/>
      </reference>
      <name value="BSJ-ObservationSPLASCH-040"/>
      <description value="An instance of SPLASCH Observation ObservationSPLASCH-040"/>
      <exampleBoolean value="true"/>
    </resource>
    <resource>
      <extension url="http://hl7.org/fhir/tools/StructureDefinition/resource-information">
        <valueString value="Observation"/>
      </extension>
      <reference>
        <reference value="Observation/BSJ-ObservationSPLASCH-041"/>
      </reference>
      <name value="BSJ-ObservationSPLASCH-041"/>
      <description value="An instance of SPLASCH Observation ObservationSPLASCH-041"/>
      <exampleBoolean value="true"/>
    </resource>
    <resource>
      <extension url="http://hl7.org/fhir/tools/StructureDefinition/resource-information">
        <valueString value="Observation"/>
      </extension>
      <reference>
        <reference value="Observation/BSJ-ObservationSPLASCH-042"/>
      </reference>
      <name value="BSJ-ObservationSPLASCH-042"/>
      <description value="An instance of SPLASCH Observation ObservationSPLASCH-042"/>
      <exampleBoolean value="true"/>
    </resource>
    <resource>
      <extension url="http://hl7.org/fhir/tools/StructureDefinition/resource-information">
        <valueString value="Observation"/>
      </extension>
      <reference>
        <reference value="Observation/BSJ-ObservationSPLASCH-043"/>
      </reference>
      <name value="BSJ-ObservationSPLASCH-043"/>
      <description value="An instance of SPLASCH Observation ObservationSPLASCH-043"/>
      <exampleBoolean value="true"/>
    </resource>
    <resource>
      <extension url="http://hl7.org/fhir/tools/StructureDefinition/resource-information">
        <valueString value="Observation"/>
      </extension>
      <reference>
        <reference value="Observation/BSJ-ObservationSPLASCH-044"/>
      </reference>
      <name value="BSJ-ObservationSPLASCH-044"/>
      <description value="An instance of SPLASCH Observation ObservationSPLASCH-044"/>
      <exampleBoolean value="true"/>
    </resource>
    <resource>
      <extension url="http://hl7.org/fhir/tools/StructureDefinition/resource-information">
        <valueString value="Observation"/>
      </extension>
      <reference>
        <reference value="Observation/BSJ-ObservationSPLASCH-045"/>
      </reference>
      <name value="BSJ-ObservationSPLASCH-045"/>
      <description value="An instance of SPLASCH Observation ObservationSPLASCH-045"/>
      <exampleBoolean value="true"/>
    </resource>
    <resource>
      <extension url="http://hl7.org/fhir/tools/StructureDefinition/resource-information">
        <valueString value="Observation"/>
      </extension>
      <reference>
        <reference value="Observation/BSJ-ObservationSPLASCH-046"/>
      </reference>
      <name value="BSJ-ObservationSPLASCH-046"/>
      <description value="An instance of SPLASCH Observation ObservationSPLASCH-046"/>
      <exampleBoolean value="true"/>
    </resource>
    <resource>
      <extension url="http://hl7.org/fhir/tools/StructureDefinition/resource-information">
        <valueString value="Observation"/>
      </extension>
      <reference>
        <reference value="Observation/BSJ-ObservationSPLASCH-047"/>
      </reference>
      <name value="BSJ-ObservationSPLASCH-047"/>
      <description value="An instance of SPLASCH Observation ObservationSPLASCH-047"/>
      <exampleBoolean value="true"/>
    </resource>
    <resource>
      <extension url="http://hl7.org/fhir/tools/StructureDefinition/resource-information">
        <valueString value="Observation"/>
      </extension>
      <reference>
        <reference value="Observation/BSJ-ObservationSPLASCH-048"/>
      </reference>
      <name value="BSJ-ObservationSPLASCH-048"/>
      <description value="An instance of SPLASCH Observation ObservationSPLASCH-048"/>
      <exampleBoolean value="true"/>
    </resource>
    <resource>
      <extension url="http://hl7.org/fhir/tools/StructureDefinition/resource-information">
        <valueString value="Observation"/>
      </extension>
      <reference>
        <reference value="Observation/BSJ-ObservationSPLASCH-049"/>
      </reference>
      <name value="BSJ-ObservationSPLASCH-049"/>
      <description value="An instance of SPLASCH Observation ObservationSPLASCH-049"/>
      <exampleBoolean value="true"/>
    </resource>
    <resource>
      <extension url="http://hl7.org/fhir/tools/StructureDefinition/resource-information">
        <valueString value="Observation"/>
      </extension>
      <reference>
        <reference value="Observation/BSJ-ObservationSPLASCH-050"/>
      </reference>
      <name value="BSJ-ObservationSPLASCH-050"/>
      <description value="An instance of SPLASCH Observation ObservationSPLASCH-050"/>
      <exampleBoolean value="true"/>
    </resource>
    <resource>
      <extension url="http://hl7.org/fhir/tools/StructureDefinition/resource-information">
        <valueString value="Observation"/>
      </extension>
      <reference>
        <reference value="Observation/BSJ-ObservationSPLASCH-051"/>
      </reference>
      <name value="BSJ-ObservationSPLASCH-051"/>
      <description value="An instance of SPLASCH Observation ObservationSPLASCH-051"/>
      <exampleBoolean value="true"/>
    </resource>
    <resource>
      <extension url="http://hl7.org/fhir/tools/StructureDefinition/resource-information">
        <valueString value="Observation"/>
      </extension>
      <reference>
        <reference value="Observation/BSJ-ObservationSPLASCH-052"/>
      </reference>
      <name value="BSJ-ObservationSPLASCH-052"/>
      <description value="An instance of SPLASCH Observation ObservationSPLASCH-052"/>
      <exampleBoolean value="true"/>
    </resource>
    <resource>
      <extension url="http://hl7.org/fhir/tools/StructureDefinition/resource-information">
        <valueString value="Observation"/>
      </extension>
      <reference>
        <reference value="Observation/BSJ-ObservationSPLASCH-053"/>
      </reference>
      <name value="BSJ-ObservationSPLASCH-053"/>
      <description value="An instance of SPLASCH Observation ObservationSPLASCH-053"/>
      <exampleBoolean value="true"/>
    </resource>
    <resource>
      <extension url="http://hl7.org/fhir/tools/StructureDefinition/resource-information">
        <valueString value="Observation"/>
      </extension>
      <reference>
        <reference value="Observation/BSJ-ObservationSPLASCH-054"/>
      </reference>
      <name value="BSJ-ObservationSPLASCH-054"/>
      <description value="An instance of SPLASCH Observation ObservationSPLASCH-054"/>
      <exampleBoolean value="true"/>
    </resource>
    <resource>
      <extension url="http://hl7.org/fhir/tools/StructureDefinition/resource-information">
        <valueString value="Observation"/>
      </extension>
      <reference>
        <reference value="Observation/BSJ-ObservationSPLASCH-055"/>
      </reference>
      <name value="BSJ-ObservationSPLASCH-055"/>
      <description value="An instance of SPLASCH Observation ObservationSPLASCH-055"/>
      <exampleBoolean value="true"/>
    </resource>
    <resource>
      <extension url="http://hl7.org/fhir/tools/StructureDefinition/resource-information">
        <valueString value="Observation"/>
      </extension>
      <reference>
        <reference value="Observation/BSJ-ObservationSPLASCH-056"/>
      </reference>
      <name value="BSJ-ObservationSPLASCH-056"/>
      <description value="An instance of SPLASCH Observation ObservationSPLASCH-056"/>
      <exampleBoolean value="true"/>
    </resource>
    <resource>
      <extension url="http://hl7.org/fhir/tools/StructureDefinition/resource-information">
        <valueString value="Observation"/>
      </extension>
      <reference>
        <reference value="Observation/BSJ-ObservationSPLASCH-057"/>
      </reference>
      <name value="BSJ-ObservationSPLASCH-057"/>
      <description value="An instance of SPLASCH Observation ObservationSPLASCH-057"/>
      <exampleBoolean value="true"/>
    </resource>
    <resource>
      <extension url="http://hl7.org/fhir/tools/StructureDefinition/resource-information">
        <valueString value="Observation"/>
      </extension>
      <reference>
        <reference value="Observation/BSJ-ObservationSPLASCH-058"/>
      </reference>
      <name value="BSJ-ObservationSPLASCH-058"/>
      <description value="An instance of SPLASCH Observation ObservationSPLASCH-058"/>
      <exampleBoolean value="true"/>
    </resource>
    <resource>
      <extension url="http://hl7.org/fhir/tools/StructureDefinition/resource-information">
        <valueString value="Observation"/>
      </extension>
      <reference>
        <reference value="Observation/BSJ-ObservationSPLASCH-059"/>
      </reference>
      <name value="BSJ-ObservationSPLASCH-059"/>
      <description value="An instance of SPLASCH Observation ObservationSPLASCH-059"/>
      <exampleBoolean value="true"/>
    </resource>
    <resource>
      <extension url="http://hl7.org/fhir/tools/StructureDefinition/resource-information">
        <valueString value="Observation"/>
      </extension>
      <reference>
        <reference value="Observation/BSJ-ObservationSPLASCH-060"/>
      </reference>
      <name value="BSJ-ObservationSPLASCH-060"/>
      <description value="An instance of SPLASCH Observation ObservationSPLASCH-060"/>
      <exampleBoolean value="true"/>
    </resource>
    <resource>
      <extension url="http://hl7.org/fhir/tools/StructureDefinition/resource-information">
        <valueString value="Observation"/>
      </extension>
      <reference>
        <reference value="Observation/BSJ-ObservationSPLASCH-061"/>
      </reference>
      <name value="BSJ-ObservationSPLASCH-061"/>
      <description value="An instance of SPLASCH Observation ObservationSPLASCH-061"/>
      <exampleBoolean value="true"/>
    </resource>
    <resource>
      <extension url="http://hl7.org/fhir/tools/StructureDefinition/resource-information">
        <valueString value="Observation"/>
      </extension>
      <reference>
        <reference value="Observation/BSJ-ObservationSPLASCH-062"/>
      </reference>
      <name value="BSJ-ObservationSPLASCH-062"/>
      <description value="An instance of SPLASCH Observation ObservationSPLASCH-062"/>
      <exampleBoolean value="true"/>
    </resource>
    <resource>
      <extension url="http://hl7.org/fhir/tools/StructureDefinition/resource-information">
        <valueString value="Observation"/>
      </extension>
      <reference>
        <reference value="Observation/BSJ-ObservationSPLASCH-063"/>
      </reference>
      <name value="BSJ-ObservationSPLASCH-063"/>
      <description value="An instance of SPLASCH Observation ObservationSPLASCH-063"/>
      <exampleBoolean value="true"/>
    </resource>
    <resource>
      <extension url="http://hl7.org/fhir/tools/StructureDefinition/resource-information">
        <valueString value="Observation"/>
      </extension>
      <reference>
        <reference value="Observation/BSJ-ObservationSPLASCH-064"/>
      </reference>
      <name value="BSJ-ObservationSPLASCH-064"/>
      <description value="An instance of SPLASCH Observation ObservationSPLASCH-064"/>
      <exampleBoolean value="true"/>
    </resource>
    <resource>
      <extension url="http://hl7.org/fhir/tools/StructureDefinition/resource-information">
        <valueString value="Observation"/>
      </extension>
      <reference>
        <reference value="Observation/BSJ-ObservationSPLASCH-065"/>
      </reference>
      <name value="BSJ-ObservationSPLASCH-065"/>
      <description value="An instance of SPLASCH Observation ObservationSPLASCH-065"/>
      <exampleBoolean value="true"/>
    </resource>
    <resource>
      <extension url="http://hl7.org/fhir/tools/StructureDefinition/resource-information">
        <valueString value="Observation"/>
      </extension>
      <reference>
        <reference value="Observation/BSJ-ObservationSPLASCH-066"/>
      </reference>
      <name value="BSJ-ObservationSPLASCH-066"/>
      <description value="An instance of SPLASCH Observation ObservationSPLASCH-066"/>
      <exampleBoolean value="true"/>
    </resource>
    <resource>
      <extension url="http://hl7.org/fhir/tools/StructureDefinition/resource-information">
        <valueString value="Observation"/>
      </extension>
      <reference>
        <reference value="Observation/BSJ-ObservationSPLASCH-067"/>
      </reference>
      <name value="BSJ-ObservationSPLASCH-067"/>
      <description value="An instance of SPLASCH Observation ObservationSPLASCH-067"/>
      <exampleBoolean value="true"/>
    </resource>
    <resource>
      <extension url="http://hl7.org/fhir/tools/StructureDefinition/resource-information">
        <valueString value="Observation"/>
      </extension>
      <reference>
        <reference value="Observation/BSJ-ObservationSPLASCH-068"/>
      </reference>
      <name value="BSJ-ObservationSPLASCH-068"/>
      <description value="An instance of SPLASCH Observation ObservationSPLASCH-068"/>
      <exampleBoolean value="true"/>
    </resource>
    <resource>
      <extension url="http://hl7.org/fhir/tools/StructureDefinition/resource-information">
        <valueString value="Observation"/>
      </extension>
      <reference>
        <reference value="Observation/BSJ-ObservationSPLASCH-069"/>
      </reference>
      <name value="BSJ-ObservationSPLASCH-069"/>
      <description value="An instance of SPLASCH Observation ObservationSPLASCH-069"/>
      <exampleBoolean value="true"/>
    </resource>
    <resource>
      <extension url="http://hl7.org/fhir/tools/StructureDefinition/resource-information">
        <valueString value="Observation"/>
      </extension>
      <reference>
        <reference value="Observation/BSJ-ObservationSPLASCH-070"/>
      </reference>
      <name value="BSJ-ObservationSPLASCH-070"/>
      <description value="An instance of SPLASCH Observation ObservationSPLASCH-070"/>
      <exampleBoolean value="true"/>
    </resource>
    <resource>
      <extension url="http://hl7.org/fhir/tools/StructureDefinition/resource-information">
        <valueString value="Observation"/>
      </extension>
      <reference>
        <reference value="Observation/BSJ-ObservationSPLASCH-071"/>
      </reference>
      <name value="BSJ-ObservationSPLASCH-071"/>
      <description value="An instance of SPLASCH Observation ObservationSPLASCH-071"/>
      <exampleBoolean value="true"/>
    </resource>
    <resource>
      <extension url="http://hl7.org/fhir/tools/StructureDefinition/resource-information">
        <valueString value="Observation"/>
      </extension>
      <reference>
        <reference value="Observation/BSJ-ObservationSPLASCH-072"/>
      </reference>
      <name value="BSJ-ObservationSPLASCH-072"/>
      <description value="An instance of SPLASCH Observation ObservationSPLASCH-072"/>
      <exampleBoolean value="true"/>
    </resource>
    <resource>
      <extension url="http://hl7.org/fhir/tools/StructureDefinition/resource-information">
        <valueString value="Observation"/>
      </extension>
      <reference>
        <reference value="Observation/BSJ-ObservationSPLASCH-073"/>
      </reference>
      <name value="BSJ-ObservationSPLASCH-073"/>
      <description value="An instance of SPLASCH Observation ObservationSPLASCH-073"/>
      <exampleBoolean value="true"/>
    </resource>
    <resource>
      <extension url="http://hl7.org/fhir/tools/StructureDefinition/resource-information">
        <valueString value="Observation"/>
      </extension>
      <reference>
        <reference value="Observation/BSJ-ObservationSPLASCH-074"/>
      </reference>
      <name value="BSJ-ObservationSPLASCH-074"/>
      <description value="An instance of SPLASCH Observation ObservationSPLASCH-074"/>
      <exampleBoolean value="true"/>
    </resource>
    <resource>
      <extension url="http://hl7.org/fhir/tools/StructureDefinition/resource-information">
        <valueString value="Observation"/>
      </extension>
      <reference>
        <reference value="Observation/BSJ-ObservationSPLASCH-075"/>
      </reference>
      <name value="BSJ-ObservationSPLASCH-075"/>
      <description value="An instance of SPLASCH Observation ObservationSPLASCH-075"/>
      <exampleBoolean value="true"/>
    </resource>
    <resource>
      <extension url="http://hl7.org/fhir/tools/StructureDefinition/resource-information">
        <valueString value="Observation"/>
      </extension>
      <reference>
        <reference value="Observation/BSJ-ObservationSPLASCH-076"/>
      </reference>
      <name value="BSJ-ObservationSPLASCH-076"/>
      <description value="An instance of SPLASCH Observation ObservationSPLASCH-076"/>
      <exampleBoolean value="true"/>
    </resource>
    <resource>
      <extension url="http://hl7.org/fhir/tools/StructureDefinition/resource-information">
        <valueString value="Observation"/>
      </extension>
      <reference>
        <reference value="Observation/BSJ-ObservationSPLASCH-077"/>
      </reference>
      <name value="BSJ-ObservationSPLASCH-077"/>
      <description value="An instance of SPLASCH Observation ObservationSPLASCH-077"/>
      <exampleBoolean value="true"/>
    </resource>
    <resource>
      <extension url="http://hl7.org/fhir/tools/StructureDefinition/resource-information">
        <valueString value="Observation"/>
      </extension>
      <reference>
        <reference value="Observation/BSJ-ObservationSPLASCH-078"/>
      </reference>
      <name value="BSJ-ObservationSPLASCH-078"/>
      <description value="An instance of SPLASCH Observation ObservationSPLASCH-078"/>
      <exampleBoolean value="true"/>
    </resource>
    <resource>
      <extension url="http://hl7.org/fhir/tools/StructureDefinition/resource-information">
        <valueString value="Observation"/>
      </extension>
      <reference>
        <reference value="Observation/BSJ-ObservationSPLASCH-079"/>
      </reference>
      <name value="BSJ-ObservationSPLASCH-079"/>
      <description value="An instance of SPLASCH Observation ObservationSPLASCH-079"/>
      <exampleBoolean value="true"/>
    </resource>
    <resource>
      <extension url="http://hl7.org/fhir/tools/StructureDefinition/resource-information">
        <valueString value="Observation"/>
      </extension>
      <reference>
        <reference value="Observation/BSJ-ObservationSPLASCH-080"/>
      </reference>
      <name value="BSJ-ObservationSPLASCH-080"/>
      <description value="An instance of SPLASCH Observation ObservationSPLASCH-080"/>
      <exampleBoolean value="true"/>
    </resource>
    <resource>
      <extension url="http://hl7.org/fhir/tools/StructureDefinition/resource-information">
        <valueString value="Observation"/>
      </extension>
      <reference>
        <reference value="Observation/BSJ-ObservationSPLASCH-081"/>
      </reference>
      <name value="BSJ-ObservationSPLASCH-081"/>
      <description value="An instance of SPLASCH Observation ObservationSPLASCH-081"/>
      <exampleBoolean value="true"/>
    </resource>
    <resource>
      <extension url="http://hl7.org/fhir/tools/StructureDefinition/resource-information">
        <valueString value="Observation"/>
      </extension>
      <reference>
        <reference value="Observation/BSJ-ObservationSPLASCH-082"/>
      </reference>
      <name value="BSJ-ObservationSPLASCH-082"/>
      <description value="An instance of SPLASCH Observation ObservationSPLASCH-082"/>
      <exampleBoolean value="true"/>
    </resource>
    <resource>
      <extension url="http://hl7.org/fhir/tools/StructureDefinition/resource-information">
        <valueString value="Observation"/>
      </extension>
      <reference>
        <reference value="Observation/BSJ-ObservationSPLASCH-083"/>
      </reference>
      <name value="BSJ-ObservationSPLASCH-083"/>
      <description value="An instance of SPLASCH Observation ObservationSPLASCH-083"/>
      <exampleBoolean value="true"/>
    </resource>
    <resource>
      <extension url="http://hl7.org/fhir/tools/StructureDefinition/resource-information">
        <valueString value="Observation"/>
      </extension>
      <reference>
        <reference value="Observation/BSJ-ObservationSPLASCH-084"/>
      </reference>
      <name value="BSJ-ObservationSPLASCH-084"/>
      <description value="An instance of SPLASCH Observation ObservationSPLASCH-084"/>
      <exampleBoolean value="true"/>
    </resource>
    <resource>
      <extension url="http://hl7.org/fhir/tools/StructureDefinition/resource-information">
        <valueString value="Observation"/>
      </extension>
      <reference>
        <reference value="Observation/BSJ-ObservationSPLASCH-085"/>
      </reference>
      <name value="BSJ-ObservationSPLASCH-085"/>
      <description value="An instance of SPLASCH Observation ObservationSPLASCH-085"/>
      <exampleBoolean value="true"/>
    </resource>
    <resource>
      <extension url="http://hl7.org/fhir/tools/StructureDefinition/resource-information">
        <valueString value="Observation"/>
      </extension>
      <reference>
        <reference value="Observation/BSJ-ObservationSPLASCH-086"/>
      </reference>
      <name value="BSJ-ObservationSPLASCH-086"/>
      <description value="An instance of SPLASCH Observation ObservationSPLASCH-086"/>
      <exampleBoolean value="true"/>
    </resource>
    <resource>
      <extension url="http://hl7.org/fhir/tools/StructureDefinition/resource-information">
        <valueString value="Observation"/>
      </extension>
      <reference>
        <reference value="Observation/BSJ-ObservationSPLASCH-087"/>
      </reference>
      <name value="BSJ-ObservationSPLASCH-087"/>
      <description value="An instance of SPLASCH Observation ObservationSPLASCH-087"/>
      <exampleBoolean value="true"/>
    </resource>
    <resource>
      <extension url="http://hl7.org/fhir/tools/StructureDefinition/resource-information">
        <valueString value="Observation"/>
      </extension>
      <reference>
        <reference value="Observation/BSJ-ObservationSPLASCH-088"/>
      </reference>
      <name value="BSJ-ObservationSPLASCH-088"/>
      <description value="An instance of SPLASCH Observation ObservationSPLASCH-088"/>
      <exampleBoolean value="true"/>
    </resource>
    <resource>
      <extension url="http://hl7.org/fhir/tools/StructureDefinition/resource-information">
        <valueString value="Observation"/>
      </extension>
      <reference>
        <reference value="Observation/BSJ-ObservationSPLASCH-089"/>
      </reference>
      <name value="BSJ-ObservationSPLASCH-089"/>
      <description value="An instance of SPLASCH Observation ObservationSPLASCH-089"/>
      <exampleBoolean value="true"/>
    </resource>
    <resource>
      <extension url="http://hl7.org/fhir/tools/StructureDefinition/resource-information">
        <valueString value="Observation"/>
      </extension>
      <reference>
        <reference value="Observation/BSJ-ObservationSPLASCH-090"/>
      </reference>
      <name value="BSJ-ObservationSPLASCH-090"/>
      <description value="An instance of SPLASCH Observation ObservationSPLASCH-090"/>
      <exampleBoolean value="true"/>
    </resource>
    <resource>
      <extension url="http://hl7.org/fhir/tools/StructureDefinition/resource-information">
        <valueString value="Observation"/>
      </extension>
      <reference>
        <reference value="Observation/BSJ-ObservationSPLASCH-091"/>
      </reference>
      <name value="BSJ-ObservationSPLASCH-091"/>
      <description value="An instance of SPLASCH Observation ObservationSPLASCH-091"/>
      <exampleBoolean value="true"/>
    </resource>
    <resource>
      <extension url="http://hl7.org/fhir/tools/StructureDefinition/resource-information">
        <valueString value="Observation"/>
      </extension>
      <reference>
        <reference value="Observation/BSJ-ObservationSPLASCH-092"/>
      </reference>
      <name value="BSJ-ObservationSPLASCH-092"/>
      <description value="An instance of SPLASCH Observation ObservationSPLASCH-092"/>
      <exampleBoolean value="true"/>
    </resource>
    <resource>
      <extension url="http://hl7.org/fhir/tools/StructureDefinition/resource-information">
        <valueString value="Observation"/>
      </extension>
      <reference>
        <reference value="Observation/BSJ-ObservationSPLASCH-093"/>
      </reference>
      <name value="BSJ-ObservationSPLASCH-093"/>
      <description value="An instance of SPLASCH Observation ObservationSPLASCH-093"/>
      <exampleBoolean value="true"/>
    </resource>
    <resource>
      <extension url="http://hl7.org/fhir/tools/StructureDefinition/resource-information">
        <valueString value="Observation"/>
      </extension>
      <reference>
        <reference value="Observation/BSJ-ObservationSPLASCH-094"/>
      </reference>
      <name value="BSJ-ObservationSPLASCH-094"/>
      <description value="An instance of SPLASCH Observation ObservationSPLASCH-094"/>
      <exampleBoolean value="true"/>
    </resource>
    <resource>
      <extension url="http://hl7.org/fhir/tools/StructureDefinition/resource-information">
        <valueString value="Observation"/>
      </extension>
      <reference>
        <reference value="Observation/BSJ-ObservationSPLASCH-095"/>
      </reference>
      <name value="BSJ-ObservationSPLASCH-095"/>
      <description value="An instance of SPLASCH Observation ObservationSPLASCH-095"/>
      <exampleBoolean value="true"/>
    </resource>
    <resource>
      <extension url="http://hl7.org/fhir/tools/StructureDefinition/resource-information">
        <valueString value="Observation"/>
      </extension>
      <reference>
        <reference value="Observation/BSJ-ObservationSPLASCH-096"/>
      </reference>
      <name value="BSJ-ObservationSPLASCH-096"/>
      <description value="An instance of SPLASCH Observation ObservationSPLASCH-096"/>
      <exampleBoolean value="true"/>
    </resource>
    <resource>
      <extension url="http://hl7.org/fhir/tools/StructureDefinition/resource-information">
        <valueString value="Observation"/>
      </extension>
      <reference>
        <reference value="Observation/BSJ-ObservationSPLASCH-097"/>
      </reference>
      <name value="BSJ-ObservationSPLASCH-097"/>
      <description value="An instance of SPLASCH Observation ObservationSPLASCH-097"/>
      <exampleBoolean value="true"/>
    </resource>
    <resource>
      <extension url="http://hl7.org/fhir/tools/StructureDefinition/resource-information">
        <valueString value="Observation"/>
      </extension>
      <reference>
        <reference value="Observation/BSJ-ObservationSPLASCH-098"/>
      </reference>
      <name value="BSJ-ObservationSPLASCH-098"/>
      <description value="An instance of SPLASCH Observation ObservationSPLASCH-098"/>
      <exampleBoolean value="true"/>
    </resource>
    <resource>
      <extension url="http://hl7.org/fhir/tools/StructureDefinition/resource-information">
        <valueString value="Observation"/>
      </extension>
      <reference>
        <reference value="Observation/BSJ-ObservationSPLASCH-099"/>
      </reference>
      <name value="BSJ-ObservationSPLASCH-099"/>
      <description value="An instance of SPLASCH Observation ObservationSPLASCH-099"/>
      <exampleBoolean value="true"/>
    </resource>
    <resource>
      <extension url="http://hl7.org/fhir/tools/StructureDefinition/resource-information">
        <valueString value="Observation"/>
      </extension>
      <reference>
        <reference value="Observation/BSJ-ObservationSPLASCH-100"/>
      </reference>
      <name value="BSJ-ObservationSPLASCH-100"/>
      <description value="An instance of SPLASCH Observation ObservationSPLASCH-100"/>
      <exampleBoolean value="true"/>
    </resource>
    <resource>
      <extension url="http://hl7.org/fhir/tools/StructureDefinition/resource-information">
        <valueString value="Observation"/>
      </extension>
      <reference>
        <reference value="Observation/BSJ-ObservationSPLASCH-101"/>
      </reference>
      <name value="BSJ-ObservationSPLASCH-101"/>
      <description value="An instance of SPLASCH Observation ObservationSPLASCH-101"/>
      <exampleBoolean value="true"/>
    </resource>
    <resource>
      <extension url="http://hl7.org/fhir/tools/StructureDefinition/resource-information">
        <valueString value="Observation"/>
      </extension>
      <reference>
        <reference value="Observation/BSJ-ObservationSPLASCH-102"/>
      </reference>
      <name value="BSJ-ObservationSPLASCH-102"/>
      <description value="An instance of SPLASCH Observation ObservationSPLASCH-102"/>
      <exampleBoolean value="true"/>
    </resource>
    <resource>
      <extension url="http://hl7.org/fhir/tools/StructureDefinition/resource-information">
        <valueString value="Observation"/>
      </extension>
      <reference>
        <reference value="Observation/BSJ-ObservationSPLASCH-103"/>
      </reference>
      <name value="BSJ-ObservationSPLASCH-103"/>
      <description value="An instance of SPLASCH Observation ObservationSPLASCH-103"/>
      <exampleBoolean value="true"/>
    </resource>
    <resource>
      <extension url="http://hl7.org/fhir/tools/StructureDefinition/resource-information">
        <valueString value="Observation"/>
      </extension>
      <reference>
        <reference value="Observation/BSJ-ObservationSPLASCH-104"/>
      </reference>
      <name value="BSJ-ObservationSPLASCH-104"/>
      <description value="An instance of SPLASCH Observation ObservationSPLASCH-104"/>
      <exampleBoolean value="true"/>
    </resource>
    <resource>
      <extension url="http://hl7.org/fhir/tools/StructureDefinition/resource-information">
        <valueString value="Observation"/>
      </extension>
      <reference>
        <reference value="Observation/BSJ-ObservationSPLASCH-105"/>
      </reference>
      <name value="BSJ-ObservationSPLASCH-105"/>
      <description value="An instance of SPLASCH Observation ObservationSPLASCH-105"/>
      <exampleBoolean value="true"/>
    </resource>
    <resource>
      <extension url="http://hl7.org/fhir/tools/StructureDefinition/resource-information">
        <valueString value="Observation"/>
      </extension>
      <reference>
        <reference value="Observation/BSJ-ObservationSPLASCH-106"/>
      </reference>
      <name value="BSJ-ObservationSPLASCH-106"/>
      <description value="An instance of SPLASCH Observation ObservationSPLASCH-106"/>
      <exampleBoolean value="true"/>
    </resource>
    <resource>
      <extension url="http://hl7.org/fhir/tools/StructureDefinition/resource-information">
        <valueString value="Patient"/>
      </extension>
      <reference>
        <reference value="Patient/BSJ-patientBSJ1"/>
      </reference>
      <name value="BSJ-patientBSJ1"/>
      <description value="An instance of USCorePatientProfile"/>
      <exampleBoolean value="true"/>
    </resource>
    <resource>
      <extension url="http://hl7.org/fhir/tools/StructureDefinition/resource-information">
        <valueString value="Organization"/>
      </extension>
      <reference>
        <reference value="Organization/Organization-Happy-Nursing-Facility"/>
      </reference>
      <name value="Organization-Happy-Nursing-Facility"/>
      <description value="An instance of Organization"/>
      <exampleBoolean value="true"/>
    </resource>
    <resource>
      <extension url="http://hl7.org/fhir/tools/StructureDefinition/resource-information">
        <valueString value="Organization"/>
      </extension>
      <reference>
        <reference value="Organization/Organization-San-Antonio-General-Hospital"/>
      </reference>
      <name value="Organization-San-Antonio-General-Hospital"/>
      <description value="An instance of Organization"/>
      <exampleBoolean value="true"/>
    </resource>
    <resource>
      <extension url="http://hl7.org/fhir/tools/StructureDefinition/resource-information">
        <valueString value="Practitioner"/>
      </extension>
      <reference>
        <reference value="Practitioner/Practitioner-AlexanderKuikhoff"/>
      </reference>
      <name value="Practitioner-AlexanderKuikhoff"/>
      <description value="An instance of Practitioner"/>
      <exampleBoolean value="true"/>
    </resource>
    <resource>
      <extension url="http://hl7.org/fhir/tools/StructureDefinition/resource-information">
        <valueString value="Practitioner"/>
      </extension>
      <reference>
        <reference value="Practitioner/Practitioner-CheriseLangford"/>
      </reference>
      <name value="Practitioner-CheriseLangford"/>
      <description value="An instance of Practitioner"/>
      <exampleBoolean value="true"/>
    </resource>
    <resource>
      <extension url="http://hl7.org/fhir/tools/StructureDefinition/resource-information">
        <valueString value="Practitioner"/>
      </extension>
      <reference>
        <reference value="Practitioner/Practitioner-DanielGranger"/>
      </reference>
      <name value="Practitioner-DanielGranger"/>
      <description value="An instance of Practitioner"/>
      <exampleBoolean value="true"/>
    </resource>
    <resource>
      <extension url="http://hl7.org/fhir/tools/StructureDefinition/resource-information">
        <valueString value="Practitioner"/>
      </extension>
      <reference>
        <reference value="Practitioner/Practitioner-DonHopmed"/>
      </reference>
      <name value="Practitioner-DonHopmed"/>
      <description value="An instance of Practitioner"/>
      <exampleBoolean value="true"/>
    </resource>
    <resource>
      <extension url="http://hl7.org/fhir/tools/StructureDefinition/resource-information">
        <valueString value="Practitioner"/>
      </extension>
      <reference>
        <reference value="Practitioner/Practitioner-JenCadbury"/>
      </reference>
      <name value="Practitioner-JenCadbury"/>
      <description value="An instance of Practitioner"/>
      <exampleBoolean value="true"/>
    </resource>
    <resource>
      <extension url="http://hl7.org/fhir/tools/StructureDefinition/resource-information">
        <valueString value="Practitioner"/>
      </extension>
      <reference>
        <reference value="Practitioner/Practitioner-JennyGlass"/>
      </reference>
      <name value="Practitioner-JennyGlass"/>
      <description value="An instance of Practitioner"/>
      <exampleBoolean value="true"/>
    </resource>
    <resource>
      <extension url="http://hl7.org/fhir/tools/StructureDefinition/resource-information">
        <valueString value="Practitioner"/>
      </extension>
      <reference>
        <reference value="Practitioner/Practitioner-JudySmiley"/>
      </reference>
      <name value="Practitioner-JudySmiley"/>
      <description value="An instance of Practitioner"/>
      <exampleBoolean value="true"/>
    </resource>
    <resource>
      <extension url="http://hl7.org/fhir/tools/StructureDefinition/resource-information">
        <valueString value="Practitioner"/>
      </extension>
      <reference>
        <reference value="Practitioner/Practitioner-LiaNguyen"/>
      </reference>
      <name value="Practitioner-LiaNguyen"/>
      <description value="An instance of Practitioner"/>
      <exampleBoolean value="true"/>
    </resource>
    <resource>
      <extension url="http://hl7.org/fhir/tools/StructureDefinition/resource-information">
        <valueString value="Practitioner"/>
      </extension>
      <reference>
        <reference value="Practitioner/Practitioner-LisaGreene"/>
      </reference>
      <name value="Practitioner-LisaGreene"/>
      <description value="An instance of Practitioner"/>
      <exampleBoolean value="true"/>
    </resource>
    <resource>
      <extension url="http://hl7.org/fhir/tools/StructureDefinition/resource-information">
        <valueString value="Practitioner"/>
      </extension>
      <reference>
        <reference value="Practitioner/Practitioner-MariaGonzalez"/>
      </reference>
      <name value="Practitioner-MariaGonzalez"/>
      <description value="An instance of Practitioner"/>
      <exampleBoolean value="true"/>
    </resource>
    <resource>
      <extension url="http://hl7.org/fhir/tools/StructureDefinition/resource-information">
        <valueString value="Practitioner"/>
      </extension>
      <reference>
        <reference value="Practitioner/Practitioner-RayMancioni"/>
      </reference>
      <name value="Practitioner-RayMancioni"/>
      <description value="An instance of Practitioner"/>
      <exampleBoolean value="true"/>
    </resource>
    <resource>
      <extension url="http://hl7.org/fhir/tools/StructureDefinition/resource-information">
        <valueString value="Practitioner"/>
      </extension>
      <reference>
        <reference value="Practitioner/Practitioner-RonMarble"/>
      </reference>
      <name value="Practitioner-RonMarble"/>
      <description value="An instance of Practitioner"/>
      <exampleBoolean value="true"/>
    </resource>
    <resource>
      <extension url="http://hl7.org/fhir/tools/StructureDefinition/resource-information">
        <valueString value="Practitioner"/>
      </extension>
      <reference>
        <reference value="Practitioner/Practitioner-SallySmith"/>
      </reference>
      <name value="Practitioner-SallySmith"/>
      <description value="An instance of Practitioner"/>
      <exampleBoolean value="true"/>
    </resource>
    <resource>
      <extension url="http://hl7.org/fhir/tools/StructureDefinition/resource-information">
        <valueString value="Practitioner"/>
      </extension>
      <reference>
        <reference value="Practitioner/Practitioner-SummerJohnson"/>
      </reference>
      <name value="Practitioner-SummerJohnson"/>
      <description value="An instance of Practitioner"/>
      <exampleBoolean value="true"/>
    </resource>
    <resource>
      <extension url="http://hl7.org/fhir/tools/StructureDefinition/resource-information">
        <valueString value="PractitionerRole"/>
      </extension>
      <reference>
        <reference value="PractitionerRole/provider-role-clinical-social-work-RayMancioni"/>
      </reference>
      <name value="provider-role-clinical-social-work-RayMancioni"/>
      <description value="An instance of PractitionerRole"/>
      <exampleBoolean value="true"/>
    </resource>
    <resource>
      <extension url="http://hl7.org/fhir/tools/StructureDefinition/resource-information">
        <valueString value="PractitionerRole"/>
      </extension>
      <reference>
        <reference value="PractitionerRole/provider-role-hospitalist-DonHopmed"/>
      </reference>
      <name value="provider-role-hospitalist-DonHopmed"/>
      <description value="An instance of PractitionerRole"/>
      <exampleBoolean value="true"/>
    </resource>
    <resource>
      <extension url="http://hl7.org/fhir/tools/StructureDefinition/resource-information">
        <valueString value="PractitionerRole"/>
      </extension>
      <reference>
        <reference value="PractitionerRole/provider-role-occupational-therapist-CheriseLangford"/>
      </reference>
      <name value="provider-role-occupational-therapist-CheriseLangford"/>
      <description value="An instance of PractitionerRole"/>
      <exampleBoolean value="true"/>
    </resource>
    <resource>
      <extension url="http://hl7.org/fhir/tools/StructureDefinition/resource-information">
        <valueString value="PractitionerRole"/>
      </extension>
      <reference>
        <reference value="PractitionerRole/provider-role-occupational-therapist-LisaGreene"/>
      </reference>
      <name value="provider-role-occupational-therapist-LisaGreene"/>
      <description value="An instance of PractitionerRole"/>
      <exampleBoolean value="true"/>
    </resource>
    <resource>
      <extension url="http://hl7.org/fhir/tools/StructureDefinition/resource-information">
        <valueString value="PractitionerRole"/>
      </extension>
      <reference>
        <reference value="PractitionerRole/provider-role-physical-therapist-DanielGranger"/>
      </reference>
      <name value="provider-role-physical-therapist-DanielGranger"/>
      <description value="An instance of PractitionerRole"/>
      <exampleBoolean value="true"/>
    </resource>
    <resource>
      <extension url="http://hl7.org/fhir/tools/StructureDefinition/resource-information">
        <valueString value="PractitionerRole"/>
      </extension>
      <reference>
        <reference value="PractitionerRole/provider-role-physical-therapist-JenCadbury"/>
      </reference>
      <name value="provider-role-physical-therapist-JenCadbury"/>
      <description value="An instance of PractitionerRole"/>
      <exampleBoolean value="true"/>
    </resource>
    <resource>
      <extension url="http://hl7.org/fhir/tools/StructureDefinition/resource-information">
        <valueString value="PractitionerRole"/>
      </extension>
      <reference>
        <reference value="PractitionerRole/provider-role-physical-therapist-RonMarble"/>
      </reference>
      <name value="provider-role-physical-therapist-RonMarble"/>
      <description value="An instance of PractitionerRole"/>
      <exampleBoolean value="true"/>
    </resource>
    <resource>
      <extension url="http://hl7.org/fhir/tools/StructureDefinition/resource-information">
        <valueString value="PractitionerRole"/>
      </extension>
      <reference>
        <reference value="PractitionerRole/provider-role-physical-therapist-SallySmith"/>
      </reference>
      <name value="provider-role-physical-therapist-SallySmith"/>
      <description value="An instance of PractitionerRole"/>
      <exampleBoolean value="true"/>
    </resource>
    <resource>
      <extension url="http://hl7.org/fhir/tools/StructureDefinition/resource-information">
        <valueString value="PractitionerRole"/>
      </extension>
      <reference>
        <reference value="PractitionerRole/provider-role-registered-nurse-JudySmiley"/>
      </reference>
      <name value="provider-role-registered-nurse-JudySmiley"/>
      <description value="An instance of PractitionerRole"/>
      <exampleBoolean value="true"/>
    </resource>
    <resource>
      <extension url="http://hl7.org/fhir/tools/StructureDefinition/resource-information">
        <valueString value="PractitionerRole"/>
      </extension>
      <reference>
        <reference value="PractitionerRole/provider-role-registered-nurse-LiaNguyen"/>
      </reference>
      <name value="provider-role-registered-nurse-LiaNguyen"/>
      <description value="An instance of PractitionerRole"/>
      <exampleBoolean value="true"/>
    </resource>
    <resource>
      <extension url="http://hl7.org/fhir/tools/StructureDefinition/resource-information">
        <valueString value="PractitionerRole"/>
      </extension>
      <reference>
        <reference value="PractitionerRole/provider-role-registered-nurse-SummerJohnson"/>
      </reference>
      <name value="provider-role-registered-nurse-SummerJohnson"/>
      <description value="An instance of PractitionerRole"/>
      <exampleBoolean value="true"/>
    </resource>
    <resource>
      <extension url="http://hl7.org/fhir/tools/StructureDefinition/resource-information">
        <valueString value="PractitionerRole"/>
      </extension>
      <reference>
        <reference value="PractitionerRole/provider-role-speech-language-pathologist-AlexanderKuikhoff"/>
      </reference>
      <name value="provider-role-speech-language-pathologist-AlexanderKuikhoff"/>
      <description value="An instance of PractitionerRole"/>
      <exampleBoolean value="true"/>
    </resource>
    <resource>
      <extension url="http://hl7.org/fhir/tools/StructureDefinition/resource-information">
        <valueString value="PractitionerRole"/>
      </extension>
      <reference>
        <reference value="PractitionerRole/provider-role-speech-language-pathologist-JennyGlass"/>
      </reference>
      <name value="provider-role-speech-language-pathologist-JennyGlass"/>
      <description value="An instance of PractitionerRole"/>
      <exampleBoolean value="true"/>
    </resource>
    <resource>
      <extension url="http://hl7.org/fhir/tools/StructureDefinition/resource-information">
        <valueString value="PractitionerRole"/>
      </extension>
      <reference>
        <reference value="PractitionerRole/provider-role-speech-language-pathologist-MariaGonzalez"/>
      </reference>
      <name value="provider-role-speech-language-pathologist-MariaGonzalez"/>
      <description value="An instance of PractitionerRole"/>
      <exampleBoolean value="true"/>
    </resource>
    <page>
      <nameUrl value="toc.html"/>
      <title value="Table of Contents"/>
      <generation value="html"/>
      <page>
        <nameUrl value="index.html"/>
        <title value="Home"/>
        <generation value="markdown"/>
      </page>
      <page>
        <nameUrl value="downloads.html"/>
        <title value="Downloads"/>
        <generation value="markdown"/>
      </page>
    </page>
    <parameter>
      <code value="path-resource"/>
      <value value="input/capabilities"/>
    </parameter>
    <parameter>
      <code value="path-resource"/>
      <value value="input/examples"/>
    </parameter>
    <parameter>
      <code value="path-resource"/>
      <value value="input/extensions"/>
    </parameter>
    <parameter>
      <code value="path-resource"/>
      <value value="input/models"/>
    </parameter>
    <parameter>
      <code value="path-resource"/>
      <value value="input/operations"/>
    </parameter>
    <parameter>
      <code value="path-resource"/>
      <value value="input/profiles"/>
    </parameter>
    <parameter>
      <code value="path-resource"/>
      <value value="input/resources"/>
    </parameter>
    <parameter>
      <code value="path-resource"/>
      <value value="input/vocabulary"/>
    </parameter>
    <parameter>
      <code value="path-resource"/>
      <value value="input/maps"/>
    </parameter>
    <parameter>
      <code value="path-resource"/>
      <value value="input/testing"/>
    </parameter>
    <parameter>
      <code value="path-resource"/>
      <value value="input/history"/>
    </parameter>
    <parameter>
      <code value="path-resource"/>
      <value value="fsh-generated/resources"/>
    </parameter>
    <parameter>
      <code value="path-pages"/>
      <value value="template/config"/>
    </parameter>
    <parameter>
      <code value="path-pages"/>
      <value value="input/images"/>
    </parameter>
    <parameter>
      <code value="path-tx-cache"/>
      <value value="input-cache/txcache"/>
    </parameter>
  </definition>
</ImplementationGuide>